evo/data_converters/obj/exporter/__init__.py
evo/data_converters/obj/exporter/evo_to_obj.py
evo/data_converters/obj/exporter/part_utils.py
evo/data_converters/obj/importer/__init__.py
evo/data_converters/obj/importer/obj_to_evo.py
evo/data_converters/obj/importer/implementation/__init__.py
evo/data_converters/obj/importer/implementation/base.py
evo/data_converters/obj/importer/implementation/tinyobj.py
evo/data_converters/obj/importer/implementation/trimesh.py
evo_data_converters_obj-0.0.1.dist-info/METADATA
evo_data_converters_obj-0.0.1.dist-info/WHEEL
evo_data_converters_obj-0.0.1.dist-info/RECORD
