Metadata-Version: 2.4
Name: evo-data-converters-obj
Version: 0.0.1
Summary: Python data converters for Wavefront Technologies OBJ/MTL file to Evo geoscience objects
Author-email: Seequent <support@seequent.com>
Requires-Python: >=3.10
Requires-Dist: evo-data-converters-common
Requires-Dist: trimesh>=4.9.0
